hybrid_garden/__init__.py
hybrid_garden/config.py
hybrid_garden/evolution.py
hybrid_garden/hg.py
hybrid_garden/initialization.py
hybrid_garden/metrics.py
hybrid_garden/models.py
hybrid_garden/params.py
hybrid_garden/selection.py
hybrid_garden/utils.py
hybrid_garden-0.1.2.dist-info/LICENSE
hybrid_garden-0.1.2.dist-info/WHEEL
hybrid_garden-0.1.2.dist-info/METADATA
hybrid_garden-0.1.2.dist-info/RECORD
