Metadata-Version: 2.1
Name: hybrid-garden
Version: 0.1.2
Summary: 
Author: Ilona Kovaleva
Author-email: iloncka.ds@gmail.com
Requires-Python: >=3.7,<3.11
Classifier: Programming Language :: Python :: 3
Classifier: Programming Language :: Python :: 3.10
Classifier: Programming Language :: Python :: 3.7
Classifier: Programming Language :: Python :: 3.8
Classifier: Programming Language :: Python :: 3.9
Requires-Dist: numpy (>=1.20.0,<2.0.0)
Requires-Dist: pmlb (>=1.0.1,<2.0.0)
Requires-Dist: pygad (>=2.16.3,<3.0.0)
Requires-Dist: randomname (>=0.1.5,<0.2.0)
Requires-Dist: scikit-learn (>=1.0.2,<2.0.0)
